rcl_action/_dummy.cpython-314t-x86_64-linux-gnu.so
ros_rcl_action-10.1.3.data/data/include/rcl_action/rcl_action/action_client.h
ros_rcl_action-10.1.3.data/data/include/rcl_action/rcl_action/action_server.h
ros_rcl_action-10.1.3.data/data/include/rcl_action/rcl_action/default_qos.h
ros_rcl_action-10.1.3.data/data/include/rcl_action/rcl_action/goal_handle.h
ros_rcl_action-10.1.3.data/data/include/rcl_action/rcl_action/goal_state_machine.h
ros_rcl_action-10.1.3.data/data/include/rcl_action/rcl_action/graph.h
ros_rcl_action-10.1.3.data/data/include/rcl_action/rcl_action/names.h
ros_rcl_action-10.1.3.data/data/include/rcl_action/rcl_action/rcl_action.h
ros_rcl_action-10.1.3.data/data/include/rcl_action/rcl_action/types.h
ros_rcl_action-10.1.3.data/data/include/rcl_action/rcl_action/version.h
ros_rcl_action-10.1.3.data/data/include/rcl_action/rcl_action/visibility_control.h
ros_rcl_action-10.1.3.data/data/include/rcl_action/rcl_action/wait.h
ros_rcl_action-10.1.3.data/data/lib/librcl_action.so
ros_rcl_action-10.1.3.data/data/share/ament_index/resource_index/package_run_dependencies/rcl_action
ros_rcl_action-10.1.3.data/data/share/ament_index/resource_index/packages/rcl_action
ros_rcl_action-10.1.3.data/data/share/ament_index/resource_index/parent_prefix_path/rcl_action
ros_rcl_action-10.1.3.data/data/share/rcl_action/local_setup.bash
ros_rcl_action-10.1.3.data/data/share/rcl_action/local_setup.dsv
ros_rcl_action-10.1.3.data/data/share/rcl_action/local_setup.sh
ros_rcl_action-10.1.3.data/data/share/rcl_action/local_setup.zsh
ros_rcl_action-10.1.3.data/data/share/rcl_action/package.dsv
ros_rcl_action-10.1.3.data/data/share/rcl_action/package.xml
ros_rcl_action-10.1.3.data/data/share/rcl_action/cmake/ament_cmake_export_dependencies-extras.cmake
ros_rcl_action-10.1.3.data/data/share/rcl_action/cmake/ament_cmake_export_include_directories-extras.cmake
ros_rcl_action-10.1.3.data/data/share/rcl_action/cmake/ament_cmake_export_libraries-extras.cmake
ros_rcl_action-10.1.3.dist-info/METADATA
ros_rcl_action-10.1.3.dist-info/WHEEL
ros_rcl_action-10.1.3.dist-info/top_level.txt
ros_rcl_action-10.1.3.dist-info/RECORD
