Metadata-Version: 2.4
Name: ros-rcl-action
Version: 10.1.3
Summary: ROS 2 package providing core C functionality for implementing and interacting with ROS 2 actions.
Requires-Dist: ros-rosidl-runtime-c~=4.9.5
Requires-Dist: ros-rmw~=7.8.2
Requires-Dist: ros-rcutils~=6.9.8
Requires-Dist: ros-rcl~=10.1.3
Requires-Dist: ros-action-msgs~=2.3.0
Dynamic: description
Dynamic: description-content-type
Dynamic: requires-dist
Dynamic: summary
